MANIFEST.in
PluginPythonRope.py
README.txt
setup.cfg
setup.py
scribes/__init__.py
scribes.python.rope.egg-info/PKG-INFO
scribes.python.rope.egg-info/SOURCES.txt
scribes.python.rope.egg-info/dependency_links.txt
scribes.python.rope.egg-info/namespace_packages.txt
scribes.python.rope.egg-info/not-zip-safe
scribes.python.rope.egg-info/requires.txt
scribes.python.rope.egg-info/top_level.txt
scribes/python/__init__.py
scribes/python/rope/__init__.py
scribes/python/rope/gui.glade
scribes/python/rope/gui.py