Metadata-Version: 1.0
Name: scribes.python.rope
Version: 0.3.3
Summary: Scribes plugin. Python code autocompleter
Home-page: http://github.com/baverman/scribes-goodies
Author: Anton Bobrov
Author-email: bobrov@vl.ru
License: UNKNOWN
Platform: UNKNOWN
